Metadata-Version: 1.1
Name: modpipe
Version: 0.0.3
Summary: A package that loads a module as a callable pipeline.
Home-page: https://github.com/jbn/modpipe
Author: John Bjorn Nelson
Author-email: jbn@abreka.com
License: MIT license
Keywords: modpipe
Platform: UNKNOWN
Classifier: Development Status :: 2 - Pre-Alpha
Classifier: Intended Audience :: Developers
Classifier: License :: OSI Approved :: MIT License
Classifier: Natural Language :: English
Classifier: Programming Language :: Python :: 2.7
Classifier: Programming Language :: Python :: 3
Classifier: Programming Language :: Python :: 3.5
Classifier: Programming Language :: Python :: 3.6
